[
  {
    "id": "9BY",
    "writer": "Shabad OS",
    "subsection": null,
    "section": "Shabad OS B",
    "sttm2_id": null,
    "lines": [
      {
        "id": "7PN5",
        "source_page": 608,
        "source_line": 1,
        "gurmukhi": "jYsy Pl qy ibrK ibrK qy hoq Pl AdBuq giq kCu khq n AwvY jI",
        "transliteration_english": "Jaisay Dhal Tay Birakh Birakh Tay Hot Dhala , Adabhout Gati Kachhu Kahat N Aavai Jee ?",
        "transliteration_hindi": "",
        "pronunciation": null,
        "pronunciation_information": null,
        "type": null,
        "translations": {
          "English": {
            "Shabad OS B": {
              "translation": "Just as a tree is born out of fruit and fruit grows on the tree this act is wonderous and cannot be explained.",
              "additional_information": null
            }
          },
          "Punjabi": {
            "Shabad OS B": {
              "translation": "",
              "additional_information": null
            }
          }
        }
      },
      {
        "id": "C14Q",
        "source_page": 608,
        "source_line": 2,
        "gurmukhi": "jYsy bws bwvn mY bwvn hY bws ibKY ibsm cirqR koaU mrm n pwvY jI",
        "transliteration_english": "Jaisay Baas Baavan Mai Baavan Hai Baas Bikhai , Bisam Charitr Kooo Maram N Paavai Jee ?",
        "transliteration_hindi": "",
        "pronunciation": null,
        "pronunciation_information": null,
        "type": null,
        "translations": {
          "English": {
            "Shabad OS B": {
              "translation": "Just as fragrance is in sandalwood and sandalwood is in fragrance, no one can know secret of this astonishing display.",
              "additional_information": null
            }
          },
          "Punjabi": {
            "Shabad OS B": {
              "translation": "",
              "additional_information": null
            }
          }
        }
      },
      {
        "id": "V532",
        "source_page": 608,
        "source_line": 3,
        "gurmukhi": "kws mY Agin Ar Agin mY kws jYsy Aiq AscrX mX kOqk khwvY jI",
        "transliteration_english": "Kaas Mai Agani Ar Agani Mai Kaas Jaisay , Ati Asacharay May Kaoutak Kahaavai Jee ?",
        "transliteration_hindi": "",
        "pronunciation": null,
        "pronunciation_information": null,
        "type": null,
        "translations": {
          "English": {
            "Shabad OS B": {
              "translation": "Just as fire exists in wood and wood is fire. This play is no less amazing.",
              "additional_information": null
            }
          },
          "Punjabi": {
            "Shabad OS B": {
              "translation": "",
              "additional_information": null
            }
          }
        }
      },
      {
        "id": "74KW",
        "source_page": 608,
        "source_line": 4,
        "gurmukhi": "siqgur mih sbd sbd mih siqgur hY ingun sgun gRXwn DRXwn smJwvY jI ]608]",
        "transliteration_english": "Satigur Mahi Sabad Sabad Mahi Satigur Hai , Nigoun Sagoun Gyaan Dhyaan Samajhaavai Jee ?608?",
        "transliteration_hindi": "",
        "pronunciation": null,
        "pronunciation_information": null,
        "type": null,
        "translations": {
          "English": {
            "Shabad OS B": {
              "translation": "Similarly, the True Guru has word (Naam) and True Guru resides in it. The True Guru alone explains us the focusing of mind on the absolute and transcendental form of divine knowledge.  (608)",
              "additional_information": null
            }
          },
          "Punjabi": {
            "Shabad OS B": {
              "translation": "",
              "additional_information": null
            }
          }
        }
      }
    ]
  }
]
